AUTHORS
CHANGES.md
LICENSE
MANIFEST.in
README.md
pyproject.toml
requirements.txt
setup.py
WakaQ.egg-info/PKG-INFO
WakaQ.egg-info/SOURCES.txt
WakaQ.egg-info/dependency_links.txt
WakaQ.egg-info/entry_points.txt
WakaQ.egg-info/requires.txt
WakaQ.egg-info/top_level.txt
wakaq/__about__.py
wakaq/__init__.py
wakaq/cli.py
wakaq/exceptions.py
wakaq/logger.py
wakaq/queue.py
wakaq/scheduler.py
wakaq/serializer.py
wakaq/task.py
wakaq/utils.py
wakaq/worker.py