Metadata-Version: 2.4
Name: WakaQ
Version: 4.0.2
Summary: Background task queue for Python backed by Redis, a minimal Celery.
Home-page: https://github.com/wakatime/wakaq
Author: Alan Hamlett
Author-email: alan.hamlett@gmail.com
License: BSD
Platform: any
Classifier: Development Status :: 5 - Production/Stable
Classifier: Intended Audience :: Developers
Classifier: Natural Language :: English
Classifier: Programming Language :: Python
Classifier: Programming Language :: Python :: 3 :: Only
Classifier: Programming Language :: Python :: 3
Classifier: Programming Language :: Python :: 3.14
Classifier: Topic :: Software Development :: Libraries :: Python Modules
Classifier: Topic :: System :: Distributed Computing
Classifier: Topic :: Software Development :: Object Brokering
Classifier: Operating System :: OS Independent
Requires-Python: >= 3.7
License-File: LICENSE
License-File: AUTHORS
Requires-Dist: click
Requires-Dist: croniter
Requires-Dist: psutil
Requires-Dist: redis
Dynamic: author
Dynamic: author-email
Dynamic: classifier
Dynamic: description
Dynamic: description-content-type
Dynamic: home-page
Dynamic: license
Dynamic: license-file
Dynamic: platform
Dynamic: requires-dist
Dynamic: requires-python
Dynamic: summary
